mjzy/MLE.py
mjzy/Var.py
mjzy/__init__.py
mjzy/covarience_matrix.py
mjzy/portfolio.py
mjzy/simulation.py
mjzy-0.3.9.dist-info/METADATA
mjzy-0.3.9.dist-info/WHEEL
mjzy-0.3.9.dist-info/top_level.txt
mjzy-0.3.9.dist-info/RECORD
